pandora_cloud/__init__.py
pandora_cloud/py.typed
pandora_cloud/server.py
pandora_cloud/flask/static/apple-touch-icon.png
pandora_cloud/flask/static/favicon-16x16.png
pandora_cloud/flask/static/favicon-32x32.png
pandora_cloud/flask/static/manifest.json
pandora_cloud/flask/static/service-worker.js
pandora_cloud/flask/static/_next/static/chunks/012ff928-bcfa62e3ac82441c.js
pandora_cloud/flask/static/_next/static/chunks/1f110208-cda4026aba1898fb.js
pandora_cloud/flask/static/_next/static/chunks/259-c6320349d8f3ff4a.js
pandora_cloud/flask/static/_next/static/chunks/58-87db5ef127e7d0b9.js
pandora_cloud/flask/static/_next/static/chunks/686-7a99a2d97a992914.js
pandora_cloud/flask/static/_next/static/chunks/68a27ff6-a453fd719d5bf767.js
pandora_cloud/flask/static/_next/static/chunks/734-99309a157861fd84.js
pandora_cloud/flask/static/_next/static/chunks/bd26816a-981e1ddc27b37cc6.js
pandora_cloud/flask/static/_next/static/chunks/framework-e23f030857e925d4.js
pandora_cloud/flask/static/_next/static/chunks/main-2f10fecca4c74462.js
pandora_cloud/flask/static/_next/static/chunks/polyfills-c67a75d1b6f99dc8.js
pandora_cloud/flask/static/_next/static/chunks/webpack-c08a82b5c21eeb39.js
pandora_cloud/flask/static/_next/static/chunks/pages/app-878ac43f93e00b3f.js
pandora_cloud/flask/static/_next/static/chunks/pages/bypass-338530f42d5b2105.js
pandora_cloud/flask/static/_next/static/chunks/pages/error-433a1bbdb23dd341.js
pandora_cloud/flask/static/_next/static/chunks/pages/index-1401d2c2b63d99cf.js
pandora_cloud/flask/static/_next/static/chunks/pages/status-6557d60655b68492.js
pandora_cloud/flask/static/_next/static/chunks/pages/account/cancel-63cd9f049103272b.js
pandora_cloud/flask/static/_next/static/chunks/pages/account/manage-6ac6d4f0510ced68.js
pandora_cloud/flask/static/_next/static/chunks/pages/account/upgrade-d6b322741680e2b4.js
pandora_cloud/flask/static/_next/static/chunks/pages/aip/pluginId/oauth/callback-389963a554a230d2.js
Pandora_Cloud_DC-0.1.0.dist-info/LICENSE
Pandora_Cloud_DC-0.1.0.dist-info/METADATA
Pandora_Cloud_DC-0.1.0.dist-info/WHEEL
Pandora_Cloud_DC-0.1.0.dist-info/top_level.txt
Pandora_Cloud_DC-0.1.0.dist-info/RECORD
